fract/VERSION
fract/__init__.py
fract/calculation_job.py
fract/colors.py
fract/export_job.py
fract/logging.py
fract/mandelbrot.py
fract/mandelbrot_calculator.py
fract/py.typed
fract/to_color.py
fract/version_func.py
fract-1.0.0a4.dist-info/LICENSE
fract-1.0.0a4.dist-info/METADATA
fract-1.0.0a4.dist-info/WHEEL
fract-1.0.0a4.dist-info/top_level.txt
fract-1.0.0a4.dist-info/RECORD
