Metadata-Version: 2.1
Name: fract
Version: 1.0.0a4
Summary: Fractal image generator
Home-page: https://github.com/cariad/fract
Author: Cariad Eccleston
Author-email: cariad@cariad.earth
License: MIT
Classifier: Development Status :: 3 - Alpha
Classifier: License :: OSI Approved :: MIT License
Classifier: Natural Language :: English
Classifier: Operating System :: OS Independent
Classifier: Programming Language :: Python :: 3 :: Only
Classifier: Programming Language :: Python :: 3.11
Classifier: Typing :: Typed
Requires-Python: >=3.11
License-File: LICENSE
Requires-Dist: pypng ~=0.20220715
